pytest_call_checker/__init__.py
pytest_call_checker/py.typed
pytest_call_checker-1.0.6.dist-info/entry_points.txt
pytest_call_checker-1.0.6.dist-info/LICENSE.md
pytest_call_checker-1.0.6.dist-info/WHEEL
pytest_call_checker-1.0.6.dist-info/METADATA
pytest_call_checker-1.0.6.dist-info/RECORD
