Metadata-Version: 2.1
Name: pytest-call-checker
Version: 1.0.6
Summary: Small pytest utility to easily create test doubles
Home-page: https://github.com/ewjoachim/pytest-call-checker
License: MIT
Keywords: pytest
Author: Joachim Jablon
Author-email: ewjoachim@gmail.com
Requires-Python: >=3.7,<4.0
Classifier: Development Status :: 4 - Beta
Classifier: Intended Audience :: Developers
Classifier: License :: OSI Approved :: MIT License
Classifier: Programming Language :: Python :: 3
Classifier: Programming Language :: Python :: 3.7
Classifier: Programming Language :: Python :: 3.8
Classifier: Programming Language :: Python :: 3.9
Classifier: Programming Language :: Python :: 3.10
Classifier: Programming Language :: Python :: 3.11
Classifier: Programming Language :: Python :: 3
Classifier: Programming Language :: Python :: 3.10
Classifier: Programming Language :: Python :: 3.7
Classifier: Programming Language :: Python :: 3.8
Classifier: Programming Language :: Python :: 3.9
Requires-Dist: pytest (>=7.1.3,<8.0.0)
Project-URL: Repository, https://github.com/ewjoachim/pytest-call-checker
